lord_rings_sdk/__init__.py
lord_rings_sdk/movie/__init__.py
lord_rings_sdk/types.py
lord_rings_sdk/utils.py
lord_rings_sdk-0.1.0.dist-info/METADATA
lord_rings_sdk-0.1.0.dist-info/WHEEL
lord_rings_sdk-0.1.0.dist-info/RECORD
