Metadata-Version: 2.1
Name: lord-rings-sdk
Version: 0.1.0
Summary: 
Author: Andres Aguirre
Author-email: andrescamiloaguirre568@gmail.com
Requires-Python: >=3.10,<4.0
Classifier: Programming Language :: Python :: 3
Classifier: Programming Language :: Python :: 3.10
Classifier: Programming Language :: Python :: 3.11
Requires-Dist: pytest (>=7.3.1,<8.0.0)
Requires-Dist: requests (>=2.28.2,<3.0.0)
Requires-Dist: requests-mock (>=1.10.0,<2.0.0)
